[
  {
    "title": "قصة تيريزا",
    "url": "https://www.9esa.com/2018/12/terreza.html",
    "published": "2018-12-13T18:01:00-02:00"
  },
  {
    "title": "قصة امرأة تدخن الرجال",
    "url": "https://www.9esa.com/2021/08/imra2a-toda5in-rijal.html",
    "published": "2021-08-27T18:00:00-02:00"
  },
  {
    "title": "قصة الزنبقة الفضية",
    "url": "https://www.9esa.com/2021/09/zinba9a-lfiddia.html",
    "published": "2021-09-19T17:57:00-02:00"
  },
  {
    "title": "قصة لا تغرنك خمرة شفتيها",
    "url": "https://www.9esa.com/2023/06/la-taghoranaka-khamrat-chafatayha.html",
    "published": "2023-06-08T18:00:00-02:00"
  }
]