[{"title":"قصة عشقك جزائي","url":"https://www.9esa.com/2019/04/3ich9oka-jaza2i.html","published":"2019-04-23T21:52:00+01:00"},{"title":"عشقك جزائي الجزء الثاني","url":"https://www.9esa.com/2019/04/3ich9oka-jaza2i-2.html","published":"2019-04-24T21:00:00+01:00"},{"title":"عشقك جزائي الجزء الثالث","url":"https://www.9esa.com/2019/04/3ich9oka-jaza2i-2_25.html","published":"2019-04-25T21:00:00+01:00"},{"title":"عشقك جزائي الجزء الرابع","url":"https://www.9esa.com/2019/04/3ich9oka-jaza2i-4.html","published":"2019-04-26T21:00:00+01:00"},{"title":"عشقك جزائي الجزء الخامس","url":"https://www.9esa.com/2019/04/3ich9oka-jaza2i-5.html","published":"2019-04-27T21:00:00+01:00"},{"title":"عشقك جزائي الجزء السادس","url":"https://www.9esa.com/2019/04/3ich9oka-jaza2i-6.html","published":"2019-04-28T21:00:00+01:00"},{"title":"عشقك جزائي الجزء السابع","url":"https://www.9esa.com/2019/04/3ich9oka-jaza2i-7.html","published":"2019-04-29T21:00:00+01:00"},{"title":"عشقك جزائي الجزء الثامن","url":"https://www.9esa.com/2019/04/3ich9oka-jaza2i-8.html","published":"2019-04-30T21:00:00+01:00"},{"title":"عشقك جزائي الجزء التاسع","url":"https://www.9esa.com/2019/05/3ich9oka-jaza2i-9.html","published":"2019-05-01T21:00:00+01:00"},{"title":"عشقك جزائي الجزء العاشر","url":"https://www.9esa.com/2019/05/3ich9oka-jaza2i-10.html","published":"2019-05-02T21:00:00+01:00"},{"title":"عشقك جزائي الجزء 11","url":"https://www.9esa.com/2019/05/3ich9oka-jaza2i-11.html","published":"2019-05-03T21:00:00+01:00"},{"title":"عشقك جزائي الجزء 12","url":"https://www.9esa.com/2019/05/3ich9oka-jaza2i-12.html","published":"2019-05-04T21:00:00+01:00"},{"title":"عشقك جزائي الجزء 13","url":"https://www.9esa.com/2019/05/3ich9oka-jaza2i-13.html","published":"2019-05-05T20:00:00Z"},{"title":"عشقك جزائي الجزء 14","url":"https://www.9esa.com/2019/05/3ich9oka-jaza2i-14.html","published":"2019-05-06T20:00:00Z"},{"title":"عشقك جزائي الجزء 15","url":"https://www.9esa.com/2019/05/3ich9oka-jaza2i-15.html","published":"2019-05-07T20:00:00Z"},{"title":"عشقك جزائي الجزء 16","url":"https://www.9esa.com/2019/05/3ich9oka-jaza2i-16.html","published":"2019-05-08T20:00:00Z"},{"title":"عشقك جزائي الجزء 17","url":"https://www.9esa.com/2019/05/3ich9oka-jaza2i-17.html","published":"2019-05-09T20:00:00Z"},{"title":"عشقك جزائي الجزء 18","url":"https://www.9esa.com/2019/05/3ich9oka-jaza2i-18.html","published":"2019-05-10T20:00:00Z"},{"title":"عشقك جزائي الجزء 19","url":"https://www.9esa.com/2019/05/3ich9oka-jaza2i-19.html","published":"2019-05-11T20:00:00Z"},{"title":"عشقك جزائي الجزء 20","url":"https://www.9esa.com/2019/05/3ich9oka-jaza2i-20.html","published":"2019-05-12T20:00:00Z"},{"title":"عشقك جزائي الجزء 21","url":"https://www.9esa.com/2019/05/3ich9oka-jaza2i-21.html","published":"2019-05-13T20:00:00Z"},{"title":"عشقك جزائي الجزء 22","url":"https://www.9esa.com/2019/05/3ich9oka-jaza2i-22.html","published":"2019-05-14T20:00:00Z"},{"title":"عشقك جزائي الجزء 23","url":"https://www.9esa.com/2019/05/3ich9oka-jaza2i-23.html","published":"2019-05-15T20:00:00Z"},{"title":"عشقك جزائي الجزء 24","url":"https://www.9esa.com/2019/05/3ich9oka-jaza2i-24.html","published":"2019-05-16T20:00:00Z"},{"title":"عشقك جزائي الجزء 25","url":"https://www.9esa.com/2019/05/3ich9oka-jaza2i-25.html","published":"2019-05-17T20:00:00Z"},{"title":"عشقك جزائي الجزء 26","url":"https://www.9esa.com/2019/05/3ich9oka-jaza2i-26.html","published":"2019-05-18T20:00:00Z"},{"title":"عشقك جزائي الجزء 27","url":"https://www.9esa.com/2019/05/3ich9oka-jaza2i-27.html","published":"2019-05-19T20:00:00Z"},{"title":"عشقك جزائي الجزء 28 والأخير","url":"https://www.9esa.com/2019/05/3ich9oka-jaza2i-28.html","published":"2019-05-20T20:00:00Z"}]