[{"title":"قصة الآغا السادي","url":"https://www.9esa.com/2018/11/elagha-elsadi.html","published":"2018-11-30T22:06:00+01:00"},{"title":"الآغا السادي الجزء الثاني","url":"https://www.9esa.com/2018/12/elagha-elsadi-2.html","published":"2018-12-01T21:00:00+01:00"},{"title":"الآغا السادي الجزء الثالث","url":"https://www.9esa.com/2018/12/elagha-elsadi-3.html","published":"2018-12-02T21:00:00+01:00"},{"title":"الآغا السادي الجزء الرابع","url":"https://www.9esa.com/2018/12/elagha-elsadi-4.html","published":"2018-12-03T21:00:00+01:00"},{"title":"الآغا السادي الجزء الخامس","url":"https://www.9esa.com/2018/12/elagha-elsadi-5.html","published":"2018-12-04T21:00:00+01:00"},{"title":"الآغا السادي الجزء السادس","url":"https://www.9esa.com/2018/12/elagha-elsadi-6.html","published":"2018-12-05T21:00:00+01:00"},{"title":"الآغا السادي الجزء السابع","url":"https://www.9esa.com/2018/12/elagha-elsadi-7.html","published":"2018-12-06T21:00:00+01:00"},{"title":"الآغا السادي الجزء الثامن","url":"https://www.9esa.com/2018/12/elagha-elsadi-8.html","published":"2018-12-07T21:00:00+01:00"},{"title":"الآغا السادي الجزء التاسع","url":"https://www.9esa.com/2018/12/elagha-elsadi-9.html","published":"2018-12-08T21:00:00+01:00"},{"title":"الآغا السادي الجزء العاشر","url":"https://www.9esa.com/2018/12/elagha-elsadi-10.html","published":"2018-12-09T21:00:00+01:00"},{"title":"الآغا السادي الجزء 11","url":"https://www.9esa.com/2018/12/elagha-elsadi-11.html","published":"2018-12-10T21:00:00+01:00"},{"title":"الآغا السادي الجزء 12","url":"https://www.9esa.com/2018/12/elagha-elsadi-12.html","published":"2018-12-11T21:00:00+01:00"},{"title":"الآغا السادي الجزء 13 والأخير","url":"https://www.9esa.com/2018/12/elagha-elsadi-13.html","published":"2018-12-12T21:00:00+01:00"}]