[{"title":"قصة راقصة و ظن أنني عاهرة فاغتصبني","url":"https://www.9esa.com/2018/01/raqisa-dana-anani-3ahira-faghtasabani.html","published":"2018-01-18T14:14:00-02:00"},{"title":"راقصة و ظن أنني عاهرة فاغتصبني الجزء الثاني","url":"https://www.9esa.com/2018/01/raqisa-dana-anani-3ahira-faghtasabani-2.html","published":"2018-01-18T14:16:00-02:00"},{"title":"راقصة و ظن أنني عاهرة فاغتصبني الجزء الثالث","url":"https://www.9esa.com/2018/01/raqisa-dana-anani-3ahira-faghtasabani-03.html","published":"2018-01-18T18:12:00-02:00"},{"title":"راقصة و ظن أنني عاهرة فاغتصبني الجزء الرابع","url":"https://www.9esa.com/2018/01/raqisa-dana-anani-3ahira-faghtasabani-04.html","published":"2018-01-19T09:55:00-02:00"},{"title":"راقصة و ظن أنني عاهرة فاغتصبني الجزء الخامس","url":"https://www.9esa.com/2018/01/raqisa-dana-anani-3ahira-faghtasabani-05.html","published":"2018-01-19T14:29:00-02:00"},{"title":"راقصة و ظن أنني عاهرة فاغتصبني الجزء السادس و الأخير","url":"https://www.9esa.com/2018/01/raqisa-dana-anani-3ahira-faghtasabani-06.html","published":"2018-01-19T14:31:00-02:00"}]