[
  {
    "title": "قصة العميل الصهيوني والجاسوسة المغربية",
    "url": "https://www.9esa.com/2021/05/l3amil-sohyoni-w-ljasosa.html",
    "published": "2021-05-20T19:00:00-02:00"
  },
  {
    "title": "العميل الصهيوني والجاسوسة المغربية الجزء الثاني",
    "url": "https://www.9esa.com/2021/05/l3amil-sohyoni-w-ljasosa-2.html",
    "published": "2021-05-21T19:00:00-02:00"
  },
  {
    "title": "العميل الصهيوني والجاسوسة المغربية الجزء الثالث",
    "url": "https://www.9esa.com/2021/05/l3amil-sohyoni-w-ljasosa-3.html",
    "published": "2021-05-22T19:00:00-02:00"
  },
  {
    "title": "العميل الصهيوني والجاسوسة المغربية الجزء الرابع",
    "url": "https://www.9esa.com/2021/05/l3amil-sohyoni-w-ljasosa-4.html",
    "published": "2021-05-23T19:00:00-02:00"
  },
  {
    "title": "العميل الصهيوني والجاسوسة المغربية الجزء الخامس",
    "url": "https://www.9esa.com/2021/05/l3amil-sohyoni-w-ljasosa-5.html",
    "published": "2021-05-24T19:00:00-02:00"
  },
  {
    "title": "العميل الصهيوني والجاسوسة المغربية الجزء السادس",
    "url": "https://www.9esa.com/2021/05/l3amil-sohyoni-w-ljasosa-6.html",
    "published": "2021-05-25T19:00:00-02:00"
  },
  {
    "title": "العميل الصهيوني والجاسوسة المغربية الجزء السابع (الفصل الثاني)",
    "url": "https://www.9esa.com/2021/05/l3amil-sohyoni-w-ljasosa-7.html",
    "published": "2021-05-26T19:00:00-02:00"
  },
  {
    "title": "العميل الصهيوني والجاسوسة المغربية الجزء الثامن",
    "url": "https://www.9esa.com/2021/05/l3amil-sohyoni-w-ljasosa-8.html",
    "published": "2021-05-27T19:00:00-02:00"
  },
  {
    "title": "العميل الصهيوني والجاسوسة المغربية الجزء التاسع",
    "url": "https://www.9esa.com/2021/05/l3amil-sohyoni-w-ljasosa-9.html",
    "published": "2021-05-28T19:00:00-02:00"
  },
  {
    "title": "العميل الصهيوني والجاسوسة المغربية الجزء العاشر",
    "url": "https://www.9esa.com/2021/05/l3amil-sohyoni-w-ljasosa-10.html",
    "published": "2021-05-29T19:00:00-02:00"
  },
  {
    "title": "العميل الصهيوني والجاسوسة المغربية الجزء 11",
    "url": "https://www.9esa.com/2021/05/l3amil-sohyoni-w-ljasosa-11.html",
    "published": "2021-05-30T19:00:00-02:00"
  },
  {
    "title": "العميل الصهيوني والجاسوسة المغربية الجزء 12",
    "url": "https://www.9esa.com/2021/05/l3amil-sohyoni-w-ljasosa-12.html",
    "published": "2021-05-31T19:00:00-02:00"
  },
  {
    "title": "العميل الصهيوني والجاسوسة المغربية الجزء 13",
    "url": "https://www.9esa.com/2021/06/l3amil-sohyoni-w-ljasosa-13.html",
    "published": "2021-06-01T19:00:00-02:00"
  },
  {
    "title": "العميل الصهيوني والجاسوسة المغربية الجزء 14",
    "url": "https://www.9esa.com/2021/06/l3amil-sohyoni-w-ljasosa-14.html",
    "published": "2021-06-02T19:00:00-02:00"
  },
  {
    "title": "العميل الصهيوني والجاسوسة المغربية الجزء 15",
    "url": "https://www.9esa.com/2021/06/l3amil-sohyoni-w-ljasosa-15.html",
    "published": "2021-06-03T19:00:00-02:00"
  },
  {
    "title": "العميل الصهيوني والجاسوسة المغربية الجزء 16",
    "url": "https://www.9esa.com/2021/06/l3amil-sohyoni-w-ljasosa-16.html",
    "published": "2021-06-04T19:00:00-02:00"
  },
  {
    "title": "العميل الصهيوني والجاسوسة المغربية الجزء 17",
    "url": "https://www.9esa.com/2021/06/l3amil-sohyoni-w-ljasosa-17.html",
    "published": "2021-06-05T19:00:00-02:00"
  },
  {
    "title": "العميل الصهيوني والجاسوسة المغربية الجزء 18 (الفصل الثالث)",
    "url": "https://www.9esa.com/2021/06/l3amil-sohyoni-w-ljasosa-18.html",
    "published": "2021-06-06T19:00:00-02:00"
  },
  {
    "title": "العميل الصهيوني والجاسوسة المغربية الجزء 19",
    "url": "https://www.9esa.com/2021/06/l3amil-sohyoni-w-ljasosa-19.html",
    "published": "2021-06-07T19:00:00-02:00"
  },
  {
    "title": "العميل الصهيوني والجاسوسة المغربية الجزء 20",
    "url": "https://www.9esa.com/2021/06/l3amil-sohyoni-w-ljasosa-20.html",
    "published": "2021-06-08T19:00:00-02:00"
  },
  {
    "title": "العميل الصهيوني والجاسوسة المغربية الجزء 21",
    "url": "https://www.9esa.com/2021/06/l3amil-sohyoni-w-ljasosa-21.html",
    "published": "2021-06-09T19:00:00-02:00"
  },
  {
    "title": "العميل الصهيوني والجاسوسة المغربية الجزء 22",
    "url": "https://www.9esa.com/2021/06/l3amil-sohyoni-w-ljasosa-22.html",
    "published": "2021-06-10T19:00:00-02:00"
  },
  {
    "title": "العميل الصهيوني والجاسوسة المغربية الجزء 23",
    "url": "https://www.9esa.com/2021/06/l3amil-sohyoni-w-ljasosa-23.html",
    "published": "2021-06-11T19:00:00-02:00"
  },
  {
    "title": "العميل الصهيوني والجاسوسة المغربية الجزء 24",
    "url": "https://www.9esa.com/2021/06/l3amil-sohyoni-w-ljasosa-24.html",
    "published": "2021-06-12T19:00:00-02:00"
  },
  {
    "title": "العميل الصهيوني والجاسوسة المغربية الجزء 25",
    "url": "https://www.9esa.com/2021/06/l3amil-sohyoni-w-ljasosa-25.html",
    "published": "2021-06-13T19:00:00-02:00"
  },
  {
    "title": "العميل الصهيوني والجاسوسة المغربية الجزء 26",
    "url": "https://www.9esa.com/2021/06/l3amil-sohyoni-w-ljasosa-26.html",
    "published": "2021-06-14T19:00:00-02:00"
  },
  {
    "title": "العميل الصهيوني والجاسوسة المغربية الجزء 27",
    "url": "https://www.9esa.com/2021/06/l3amil-sohyoni-w-ljasosa-27.html",
    "published": "2021-06-15T19:00:00-02:00"
  },
  {
    "title": "العميل الصهيوني والجاسوسة المغربية الجزء 28",
    "url": "https://www.9esa.com/2021/06/l3amil-sohyoni-w-ljasosa-28.html",
    "published": "2021-06-16T19:00:00-02:00"
  },
  {
    "title": "العميل الصهيوني والجاسوسة المغربية الجزء 29",
    "url": "https://www.9esa.com/2021/06/l3amil-sohyoni-w-ljasosa-29.html",
    "published": "2021-06-17T19:00:00-02:00"
  },
  {
    "title": "العميل الصهيوني والجاسوسة المغربية الجزء 30 والأخير",
    "url": "https://www.9esa.com/2021/06/l3amil-sohyoni-w-ljasosa-30.html",
    "published": "2021-06-18T19:00:00-02:00"
  }
]